ps_hero_fastapi_lib/__init__.py
ps_hero_fastapi_lib/model/__init__.py
ps_hero_fastapi_lib/model/dto.py
ps_hero_fastapi_lib/model/models.py
ps_hero_fastapi_lib/repository/__init__.py
ps_hero_fastapi_lib/repository/base.py
ps_hero_fastapi_lib/service/__init__.py
ps_hero_fastapi_lib/service/base.py
ps_hero_fastapi_lib/test/__init__.py
ps_hero_fastapi_lib/test/test_models.py
ps_hero_fastapi_lib/util/__init__.py
ps_hero_fastapi_lib/util/database.py
ps_hero_fastapi_lib-0.1.0.dist-info/licenses/LICENSE
ps_hero_fastapi_lib-0.1.0.dist-info/METADATA
ps_hero_fastapi_lib-0.1.0.dist-info/WHEEL
ps_hero_fastapi_lib-0.1.0.dist-info/top_level.txt
ps_hero_fastapi_lib-0.1.0.dist-info/RECORD
