Metadata-Version: 2.4
Name: ps-hero-fastapi-lib
Version: 0.1.0
Summary: Biblioteca do model de Heróis com banco de dados.
Home-page: https://github.com/douglasbolis/ps_hero_fastapi_lib
Author: Douglas Lima
Author-email: douglasbolislima@gmail.com
Classifier: Programming Language :: Python :: 3
Classifier: Operating System :: OS Independent
Requires-Python: >=3.8
License-File: LICENSE
Dynamic: author
Dynamic: author-email
Dynamic: classifier
Dynamic: description
Dynamic: description-content-type
Dynamic: home-page
Dynamic: license-file
Dynamic: requires-python
Dynamic: summary
